bundesliga_tippspiel_reminder/BundesligaTippspielReminderBot.py
bundesliga_tippspiel_reminder/BundesligaTippspielReminderParser.py
bundesliga_tippspiel_reminder/__init__.py
bundesliga_tippspiel_reminder/api.py
bundesliga_tippspiel_reminder/db/ApiKey.py
bundesliga_tippspiel_reminder/db/Reminder.py
bundesliga_tippspiel_reminder/db/__init__.py
bundesliga_tippspiel_reminder-0.3.1.data/scripts/bundesliga-tippspiel-reminder
bundesliga_tippspiel_reminder-0.3.1.dist-info/LICENSE
bundesliga_tippspiel_reminder-0.3.1.dist-info/METADATA
bundesliga_tippspiel_reminder-0.3.1.dist-info/WHEEL
bundesliga_tippspiel_reminder-0.3.1.dist-info/top_level.txt
bundesliga_tippspiel_reminder-0.3.1.dist-info/RECORD
