Metadata-Version: 2.1
Name: bundesliga-tippspiel-reminder
Version: 0.3.1
Summary: A reminder bot for bundesliga-tippspiel
Home-page: https://gitlab.namibsun.net/namibsun/python/bundesliga-tippspiel-reminder
Author: Hermann Krumrey
Author-email: hermann@krumreyh.com
License: GNU GPL3
Platform: UNKNOWN
Classifier: License :: OSI Approved :: GNU General Public License v3 (GPLv3)
Requires-Dist: typing
Requires-Dist: kudubot
Requires-Dist: bokkichat
Requires-Dist: requests
Requires-Dist: sqlalchemy
Requires-Dist: sentry-sdk
